standard_api_response/__init__.py
standard_api_response/exception.py
standard_api_response/standard_response.py
standard_api_response/standard_response_mapper.py
standard_api_response/time_utility.py
test/__init__.py
test/test.py
standard_api_response-1.3.6.dist-info/METADATA
standard_api_response-1.3.6.dist-info/WHEEL
standard_api_response-1.3.6.dist-info/top_level.txt
standard_api_response-1.3.6.dist-info/RECORD
