Metadata-Version: 2.1
Name: standard-api-response
Version: 1.3.6
Summary: Standard API response helper package
Home-page: https://github.com/jogakdal/standard-api-response
Author: 황용호
Author-email: jogakdal@gmail.com
License: UNKNOWN
Keywords: jogakdal,standard,API,response,helper,pydantic
Platform: UNKNOWN
Classifier: Programming Language :: Python :: 3
Classifier: Operating System :: OS Independent
Requires-Python: >=3.6
Requires-Dist: fastapi
Requires-Dist: inflection
Requires-Dist: convertable-key-model
